.coveragerc
.isort.cfg
CHANGES.rst
CONTRIBUTORS.rst
MANIFEST.in
README.rst
buildout.cfg
ci.cfg
requirements.txt
setup.py
buildout.d/base.cfg
buildout.d/checkouts.cfg
buildout.d/development.cfg
buildout.d/sources.cfg
buildout.d/versions.cfg
docs/LICENSE.GPL
docs/LICENSE.rst
src/collective/__init__.py
src/collective.compoundcriterion.egg-info/PKG-INFO
src/collective.compoundcriterion.egg-info/SOURCES.txt
src/collective.compoundcriterion.egg-info/dependency_links.txt
src/collective.compoundcriterion.egg-info/entry_points.txt
src/collective.compoundcriterion.egg-info/namespace_packages.txt
src/collective.compoundcriterion.egg-info/not-zip-safe
src/collective.compoundcriterion.egg-info/requires.txt
src/collective.compoundcriterion.egg-info/top_level.txt
src/collective/compoundcriterion/__init__.py
src/collective/compoundcriterion/adapters.py
src/collective/compoundcriterion/configure.zcml
src/collective/compoundcriterion/interfaces.py
src/collective/compoundcriterion/profiles.zcml
src/collective/compoundcriterion/queryparser.py
src/collective/compoundcriterion/setuphandlers.py
src/collective/compoundcriterion/testing.py
src/collective/compoundcriterion/testing.zcml
src/collective/compoundcriterion/vocabularies.py
src/collective/compoundcriterion/locales/collective.compoundcriterion.pot
src/collective/compoundcriterion/locales/update.sh
src/collective/compoundcriterion/locales/es/LC_MESSAGES/collective.compoundcriterion.po
src/collective/compoundcriterion/locales/fr/LC_MESSAGES/collective.compoundcriterion.po
src/collective/compoundcriterion/profiles/default/browserlayer.xml
src/collective/compoundcriterion/profiles/default/collectivecompoundcriterion_marker.txt
src/collective/compoundcriterion/profiles/default/metadata.xml
src/collective/compoundcriterion/profiles/default/registry.xml
src/collective/compoundcriterion/profiles/testing/metadata.xml
src/collective/compoundcriterion/tests/__init__.py
src/collective/compoundcriterion/tests/adapter.py
src/collective/compoundcriterion/tests/test_criterion.py
src/collective/compoundcriterion/tests/test_robot.py
src/collective/compoundcriterion/tests/test_setup.py
src/collective/compoundcriterion/tests/robot/.gitkeep