Metadata-Version: 2.1
Name: collective.compoundcriterion
Version: 0.7
Summary: Compound criterion for plone.app.collection managing complex query
Home-page: http://pypi.python.org/pypi/collective.compoundcriterion
Author: IMIO
Author-email: support@imio.be
License: GPL
Keywords: Plone collection criterion
Platform: UNKNOWN
Classifier: Development Status :: 6 - Mature
Classifier: Environment :: Web Environment
Classifier: Framework :: Plone
Classifier: Framework :: Plone :: 4.3
Classifier: License :: OSI Approved :: GNU General Public License (GPL)
Classifier: Programming Language :: Python
Classifier: Programming Language :: Python :: 2.7
Provides-Extra: test
